joycon_lib/__init__.py
joycon_lib/buttons.py
joycon_lib/dual_joycon.py
joycon_lib/evdev_backend.py
joycon_lib/exceptions.py
joycon_lib/joycon.py
joycon_lib/stick.py
joycon_lib-1.0.0.dist-info/licenses/LICENSE
joycon_lib-1.0.0.dist-info/METADATA
joycon_lib-1.0.0.dist-info/WHEEL
joycon_lib-1.0.0.dist-info/top_level.txt
joycon_lib-1.0.0.dist-info/RECORD
