Metadata-Version: 2.4
Name: joycon-lib
Version: 1.0.0
Summary: A Python library for reading button and stick input from Nintendo Joy-Con controllers
Author: Dexmate AI
License-Expression: MIT
Keywords: joycon,nintendo,controller,gamepad,input,evdev,linux
Classifier: Development Status :: 4 - Beta
Classifier: Intended Audience :: Developers
Classifier: Operating System :: POSIX :: Linux
Classifier: Programming Language :: Python :: 3
Classifier: Programming Language :: Python :: 3.10
Classifier: Programming Language :: Python :: 3.11
Classifier: Programming Language :: Python :: 3.12
Classifier: Programming Language :: Python :: 3.13
Classifier: Topic :: Games/Entertainment
Classifier: Topic :: Software Development :: Libraries :: Python Modules
Classifier: Topic :: System :: Hardware :: Hardware Drivers
Requires-Python: <3.14,>=3.10
License-File: LICENSE
Requires-Dist: evdev>=1.6.0
Provides-Extra: dev
Requires-Dist: pytest>=7.0; extra == "dev"
Requires-Dist: pytest-cov>=4.0; extra == "dev"
Requires-Dist: black>=23.0; extra == "dev"
Requires-Dist: isort>=5.0; extra == "dev"
Requires-Dist: mypy>=1.0; extra == "dev"
Requires-Dist: pylint>=2.0; extra == "dev"
Provides-Extra: build
Requires-Dist: nuitka>=2.0; extra == "build"
Requires-Dist: ordered-set>=4.1.0; extra == "build"
Requires-Dist: zstandard>=0.21.0; extra == "build"
Dynamic: license-file
